__init__.py
kv_segmentor/__init__.py
kv_segmentor/segmentor.py
kv_segmentor-0.1.5.dist-info/METADATA
kv_segmentor-0.1.5.dist-info/WHEEL
kv_segmentor-0.1.5.dist-info/top_level.txt
kv_segmentor-0.1.5.dist-info/RECORD
