Metadata-Version: 2.1
Name: kv-segmentor
Version: 0.1.5
Author-email: Justin Bui <jmbui@klangverso.com>
Requires-Python: >=3.8
Requires-Dist: ultralytics
Requires-Dist: chardet
Requires-Dist: opencv-python
Requires-Dist: matplotlib
